xprint/__init__.py
xprint/xprint.py
xprint-3.1.1.dist-info/LICENSE
xprint-3.1.1.dist-info/METADATA
xprint-3.1.1.dist-info/WHEEL
xprint-3.1.1.dist-info/top_level.txt
xprint-3.1.1.dist-info/RECORD
