Metadata-Version: 2.1
Name: xprint
Version: 3.1.1
Summary: xprint
Home-page: https://github.com/neoctobers/py_xprint
Author: @neoctobers
Author-email: neoctobers@gmail.com
License: UNKNOWN
Platform: UNKNOWN
Classifier: Programming Language :: Python :: 3
Classifier: License :: OSI Approved :: MIT License
Classifier: Operating System :: OS Independent
Requires-Dist: colorama
